KYMpy/CONST.py
KYMpy/GetKYM.py
KYMpy/MemePage.py
KYMpy/NewsPage.py
KYMpy/Particle.py
KYMpy/PhotoPage.py
KYMpy/SearchEngine.py
KYMpy/VideoPage.py
KYMpy/__init__.py
KYMpy-69.420.dist-info/LICENSE
KYMpy-69.420.dist-info/METADATA
KYMpy-69.420.dist-info/WHEEL
KYMpy-69.420.dist-info/top_level.txt
KYMpy-69.420.dist-info/RECORD
