Metadata-Version: 2.1
Name: KYMpy
Version: 69.420
Summary: The library to get memes from KnowYourMeme
Author: notsolitus
Author-email: notsolitus@githubmail.org
License: MIT
License-File: LICENSE
